pyease_grpc/__init__.py
pyease_grpc/_protocol.py
pyease_grpc/generator.py
pyease_grpc/protobuf.py
pyease_grpc/rpc_method.py
pyease_grpc/rpc_method_type.py
pyease_grpc/rpc_response.py
pyease_grpc/rpc_response_native.py
pyease_grpc/rpc_response_web.py
pyease_grpc/rpc_session.py
pyease_grpc/rpc_trailer.py
pyease_grpc/rpc_uri.py
pyease_grpc-1.7.1.dist-info/licenses/LICENSE
pyease_grpc-1.7.1.dist-info/METADATA
pyease_grpc-1.7.1.dist-info/WHEEL
pyease_grpc-1.7.1.dist-info/entry_points.txt
pyease_grpc-1.7.1.dist-info/top_level.txt
pyease_grpc-1.7.1.dist-info/RECORD
